nmslib.cpython-311-darwin.so
fixed_install_nmslib-2.1.2.dist-info/LICENSE
fixed_install_nmslib-2.1.2.dist-info/LICENSE-Apache-2.0
fixed_install_nmslib-2.1.2.dist-info/METADATA
fixed_install_nmslib-2.1.2.dist-info/WHEEL
fixed_install_nmslib-2.1.2.dist-info/top_level.txt
fixed_install_nmslib-2.1.2.dist-info/RECORD
