Metadata-Version: 2.1
Name: fixed-install-nmslib
Version: 2.1.2
Summary: Non-Metric Space Library (NMSLIB)
Home-page: https://github.com/nmslib/nmslib
Author: B. Naidan, L. Boytsov, Yu. Malkov, B. Frederickson, D. Novak, et al.
License-File: LICENSE
License-File: LICENSE-Apache-2.0
Requires-Dist: pybind11 >=2.2.3
Requires-Dist: psutil
Requires-Dist: numpy >=1.10.0 ; python_version >= "3.5"
